monotonic_align/__init__.py
monotonic_align/core.c
monotonic_align/core.cpython-38-x86_64-linux-gnu.so
vits_monotonic_align-0.0.3.dist-info/LICENSE
vits_monotonic_align-0.0.3.dist-info/METADATA
vits_monotonic_align-0.0.3.dist-info/WHEEL
vits_monotonic_align-0.0.3.dist-info/top_level.txt
vits_monotonic_align-0.0.3.dist-info/RECORD
