Metadata-Version: 2.1
Name: vits-monotonic-align
Version: 0.0.3
Summary: Monotonic Align from VITS
Home-page: https://github.com/mushanshanshan/monotonic_align
Author: Mushan
License: MIT
Keywords: None
Classifier: Environment :: Console
Classifier: License :: OSI Approved :: MIT License
Classifier: Programming Language :: Python :: 3.7
License-File: LICENSE
Requires-Dist: Cython
Requires-Dist: numpy
